shellcake/__init__.py
shellcake/executor.py
tests/__init__.py
tests/test_invoker.py
shellcake-0.1.0.dist-info/LICENSE
shellcake-0.1.0.dist-info/METADATA
shellcake-0.1.0.dist-info/WHEEL
shellcake-0.1.0.dist-info/top_level.txt
shellcake-0.1.0.dist-info/RECORD
