Metadata-Version: 2.1
Name: shellcake
Version: 0.1.0
Summary: A Python package to invoke shell commands with sudo and verbose options.
Home-page: https://github.com/tarcisiomiranda/shell_cake
Author: Tarcisio Miranda
Author-email: eu@tarcisio.me
Classifier: Programming Language :: Python :: 3
Classifier: Operating System :: POSIX :: Linux
Classifier: License :: OSI Approved :: MIT License
Classifier: Intended Audience :: Developers
Classifier: Topic :: Software Development :: Libraries :: Python Modules
Requires-Python: >=3.6
License-File: LICENSE
